PyRandPassword/__init__.py
PyRandPassword/constants.py
PyRandPassword/password.py
PyRandPassword/random.py
PyRandPassword-0.1.0.dist-info/METADATA
PyRandPassword-0.1.0.dist-info/WHEEL
PyRandPassword-0.1.0.dist-info/top_level.txt
PyRandPassword-0.1.0.dist-info/RECORD
